aitronos_alpha/__init__.py
aitronos_alpha/cli.py
aitronos_alpha/utils.py
aitronos_alpha/commands/__init__.py
aitronos_alpha/commands/feature_x.py
aitronos_alpha/commands/init_project.py
aitronos_alpha/commands/streamline.py
aitronos_alpha/extras/__init__.py
aitronos_cli-0.5.0.dist-info/LICENSE
aitronos_cli-0.5.0.dist-info/METADATA
aitronos_cli-0.5.0.dist-info/WHEEL
aitronos_cli-0.5.0.dist-info/entry_points.txt
aitronos_cli-0.5.0.dist-info/top_level.txt
aitronos_cli-0.5.0.dist-info/RECORD
