Metadata-Version: 2.2
Name: aitronos-cli
Version: 0.5.0
Summary: aitronos cli
Home-page: https://github.com/Freddy-Development/Aitronos-CLI
Author: Phillip Loacker
Author-email: Phillip Loacker <phillip.loacker@aitronos.com>
License: MIT License
Project-URL: Homepage, https://github.com/Freddy-Development/Aitronos-CLI
Project-URL: Repository, https://github.com/Freddy-Development/Aitronos-CLI.git
Keywords: ai,cli,development,tools
Classifier: Programming Language :: Python :: 3
Classifier: License :: OSI Approved :: MIT License
Classifier: Operating System :: OS Independent
Requires-Python: >=3.8
License-File: LICENSE
Requires-Dist: click>=8.0.0
Requires-Dist: pyyaml>=6.0.0
Dynamic: author
Dynamic: home-page
Dynamic: requires-python
